[{"__symbolic":"module","version":3,"metadata":{"DefaultService":{"__symbolic":"class","decorators":[{"__symbolic":"call","expression":{"__symbolic":"reference","module":"@angular/core","name":"Injectable"}}],"members":{"__ctor__":[{"__symbolic":"constructor","parameterDecorators":[null,[{"__symbolic":"call","expression":{"__symbolic":"reference","module":"@angular/core","name":"Optional"}},{"__symbolic":"call","expression":{"__symbolic":"reference","module":"@angular/core","name":"Inject"},"arguments":[{"__symbolic":"reference","module":"../variables","name":"BASE_PATH"}]}],[{"__symbolic":"call","expression":{"__symbolic":"reference","module":"@angular/core","name":"Optional"}}]],"parameters":[{"__symbolic":"reference","module":"@angular/http","name":"Http"},{"__symbolic":"reference","name":"string"},{"__symbolic":"reference","module":"../configuration","name":"Configuration"}]}],"extendObj":[{"__symbolic":"method"}],"canConsumeForm":[{"__symbolic":"method"}],"accountById":[{"__symbolic":"method"}],"addCardsForBank":[{"__symbolic":"method"}],"addCommentForViewOnTransaction":[{"__symbolic":"method"}],"addCounterpartyCorporateLocation":[{"__symbolic":"method"}],"addCounterpartyImageUrl":[{"__symbolic":"method"}],"addCounterpartyMoreInfo":[{"__symbolic":"method"}],"addCounterpartyOpenCorporatesUrl":[{"__symbolic":"method"}],"addCounterpartyPhysicalLocation":[{"__symbolic":"method"}],"addCounterpartyPublicAlias":[{"__symbolic":"method"}],"addCounterpartyUrl":[{"__symbolic":"method"}],"addCustomerMessage":[{"__symbolic":"method"}],"addEntitlement":[{"__symbolic":"method"}],"addImageForViewOnTransaction":[{"__symbolic":"method"}],"addKycCheck":[{"__symbolic":"method"}],"addKycDocument":[{"__symbolic":"method"}],"addKycMedia":[{"__symbolic":"method"}],"addKycStatus":[{"__symbolic":"method"}],"addOtherAccountPrivateAlias":[{"__symbolic":"method"}],"addPermissionForUserForBankAccountForMultipleViews":[{"__symbolic":"method"}],"addPermissionForUserForBankAccountForOneView":[{"__symbolic":"method"}],"addSocialMediaHandle":[{"__symbolic":"method"}],"addTagForViewOnTransaction":[{"__symbolic":"method"}],"addTransactionNarrative":[{"__symbolic":"method"}],"addWhereTagForViewOnTransaction":[{"__symbolic":"method"}],"allAccountsAtOneBank":[{"__symbolic":"method"}],"bankById":[{"__symbolic":"method"}],"config":[{"__symbolic":"method"}],"corePrivateAccountsAllBanks":[{"__symbolic":"method"}],"createAccount":[{"__symbolic":"method"}],"createAtm":[{"__symbolic":"method"}],"createBank":[{"__symbolic":"method"}],"createBranch":[{"__symbolic":"method"}],"createCounterparty":[{"__symbolic":"method"}],"createCustomer":[{"__symbolic":"method"}],"createMeeting":[{"__symbolic":"method"}],"createProduct":[{"__symbolic":"method"}],"createTransactionType":[{"__symbolic":"method"}],"createUser":[{"__symbolic":"method"}],"createUserCustomerLinks":[{"__symbolic":"method"}],"createViewForBankAccount":[{"__symbolic":"method"}],"deleteCommentForViewOnTransaction":[{"__symbolic":"method"}],"deleteCounterpartyCorporateLocation":[{"__symbolic":"method"}],"deleteCounterpartyImageUrl":[{"__symbolic":"method"}],"deleteCounterpartyMoreInfo":[{"__symbolic":"method"}],"deleteCounterpartyOpenCorporatesUrl":[{"__symbolic":"method"}],"deleteCounterpartyPhysicalLocation":[{"__symbolic":"method"}],"deleteCounterpartyPrivateAlias":[{"__symbolic":"method"}],"deleteCounterpartyPublicAlias":[{"__symbolic":"method"}],"deleteCounterpartyUrl":[{"__symbolic":"method"}],"deleteEntitlement":[{"__symbolic":"method"}],"deleteImageForViewOnTransaction":[{"__symbolic":"method"}],"deleteTagForViewOnTransaction":[{"__symbolic":"method"}],"deleteTransactionNarrative":[{"__symbolic":"method"}],"deleteViewForBankAccount":[{"__symbolic":"method"}],"deleteWhereTagForViewOnTransaction":[{"__symbolic":"method"}],"enableDisableConsumers":[{"__symbolic":"method"}],"getAdapter":[{"__symbolic":"method"}],"getAllEntitlements":[{"__symbolic":"method"}],"getAtm":[{"__symbolic":"method"}],"getAtms":[{"__symbolic":"method"}],"getBanks":[{"__symbolic":"method"}],"getBranch":[{"__symbolic":"method"}],"getBranches":[{"__symbolic":"method"}],"getCards":[{"__symbolic":"method"}],"getCardsForBank":[{"__symbolic":"method"}],"getCommentsForViewOnTransaction":[{"__symbolic":"method"}],"getConnectorMetrics":[{"__symbolic":"method"}],"getConsumer":[{"__symbolic":"method"}],"getConsumers":[{"__symbolic":"method"}],"getCoreAccountById":[{"__symbolic":"method"}],"getCoreTransactionsForBankAccount":[{"__symbolic":"method"}],"getCounterpartiesForAccount":[{"__symbolic":"method"}],"getCounterpartyPublicAlias":[{"__symbolic":"method"}],"getCrmEvents":[{"__symbolic":"method"}],"getCurrentFxRate":[{"__symbolic":"method"}],"getCurrentUser":[{"__symbolic":"method"}],"getCustomer":[{"__symbolic":"method"}],"getCustomerMessages":[{"__symbolic":"method"}],"getCustomers":[{"__symbolic":"method"}],"getEntitlements":[{"__symbolic":"method"}],"getEntitlementsByBankAndUser":[{"__symbolic":"method"}],"getImagesForViewOnTransaction":[{"__symbolic":"method"}],"getKycChecks":[{"__symbolic":"method"}],"getKycDocuments":[{"__symbolic":"method"}],"getKycMedia":[{"__symbolic":"method"}],"getKycStatuses":[{"__symbolic":"method"}],"getMeeting":[{"__symbolic":"method"}],"getMeetings":[{"__symbolic":"method"}],"getMessageDocs":[{"__symbolic":"method"}],"getMetrics":[{"__symbolic":"method"}],"getOtherAccountByIdForBankAccount":[{"__symbolic":"method"}],"getOtherAccountForTransaction":[{"__symbolic":"method"}],"getOtherAccountMetadata":[{"__symbolic":"method"}],"getOtherAccountPrivateAlias":[{"__symbolic":"method"}],"getOtherAccountsForBankAccount":[{"__symbolic":"method"}],"getPermissionForUserForBankAccount":[{"__symbolic":"method"}],"getPermissionsForBankAccount":[{"__symbolic":"method"}],"getProduct":[{"__symbolic":"method"}],"getProducts":[{"__symbolic":"method"}],"getRoles":[{"__symbolic":"method"}],"getSocialMediaHandles":[{"__symbolic":"method"}],"getTagsForViewOnTransaction":[{"__symbolic":"method"}],"getTransactionByIdForBankAccount":[{"__symbolic":"method"}],"getTransactionNarrative":[{"__symbolic":"method"}],"getTransactionRequestTypes":[{"__symbolic":"method"}],"getTransactionRequestTypesSupportedByBank":[{"__symbolic":"method"}],"getTransactionRequests":[{"__symbolic":"method"}],"getTransactionTypes":[{"__symbolic":"method"}],"getTransactionsForBankAccount":[{"__symbolic":"method"}],"getUser":[{"__symbolic":"method"}],"getUserByUserId":[{"__symbolic":"method"}],"getUserByUsername":[{"__symbolic":"method"}],"getUsers":[{"__symbolic":"method"}],"getViewsForBankAccount":[{"__symbolic":"method"}],"getWhereTagForViewOnTransaction":[{"__symbolic":"method"}],"privateAccountsAtOneBank":[{"__symbolic":"method"}],"publicAccountsAllBanks":[{"__symbolic":"method"}],"publicAccountsAtOneBank":[{"__symbolic":"method"}],"removePermissionForUserForBankAccountForAllViews":[{"__symbolic":"method"}],"removePermissionForUserForBankAccountForOneView":[{"__symbolic":"method"}],"root":[{"__symbolic":"method"}],"sandboxDataImport":[{"__symbolic":"method"}],"updateAccountLabel":[{"__symbolic":"method"}],"updateBranch":[{"__symbolic":"method"}],"updateConsumerRedirectUrl":[{"__symbolic":"method"}],"updateCounterpartyCorporateLocation":[{"__symbolic":"method"}],"updateCounterpartyImageUrl":[{"__symbolic":"method"}],"updateCounterpartyMoreInfo":[{"__symbolic":"method"}],"updateCounterpartyOpenCorporatesUrl":[{"__symbolic":"method"}],"updateCounterpartyPhysicalLocation":[{"__symbolic":"method"}],"updateCounterpartyPrivateAlias":[{"__symbolic":"method"}],"updateCounterpartyPublicAlias":[{"__symbolic":"method"}],"updateCounterpartyUrl":[{"__symbolic":"method"}],"updateTransactionNarrative":[{"__symbolic":"method"}],"updateViewForBankAccount":[{"__symbolic":"method"}],"updateWhereTagForViewOnTransaction":[{"__symbolic":"method"}],"accountByIdWithHttpInfo":[{"__symbolic":"method"}],"addCardsForBankWithHttpInfo":[{"__symbolic":"method"}],"addCommentForViewOnTransactionWithHttpInfo":[{"__symbolic":"method"}],"addCounterpartyCorporateLocationWithHttpInfo":[{"__symbolic":"method"}],"addCounterpartyImageUrlWithHttpInfo":[{"__symbolic":"method"}],"addCounterpartyMoreInfoWithHttpInfo":[{"__symbolic":"method"}],"addCounterpartyOpenCorporatesUrlWithHttpInfo":[{"__symbolic":"method"}],"addCounterpartyPhysicalLocationWithHttpInfo":[{"__symbolic":"method"}],"addCounterpartyPublicAliasWithHttpInfo":[{"__symbolic":"method"}],"addCounterpartyUrlWithHttpInfo":[{"__symbolic":"method"}],"addCustomerMessageWithHttpInfo":[{"__symbolic":"method"}],"addEntitlementWithHttpInfo":[{"__symbolic":"method"}],"addImageForViewOnTransactionWithHttpInfo":[{"__symbolic":"method"}],"addKycCheckWithHttpInfo":[{"__symbolic":"method"}],"addKycDocumentWithHttpInfo":[{"__symbolic":"method"}],"addKycMediaWithHttpInfo":[{"__symbolic":"method"}],"addKycStatusWithHttpInfo":[{"__symbolic":"method"}],"addOtherAccountPrivateAliasWithHttpInfo":[{"__symbolic":"method"}],"addPermissionForUserForBankAccountForMultipleViewsWithHttpInfo":[{"__symbolic":"method"}],"addPermissionForUserForBankAccountForOneViewWithHttpInfo":[{"__symbolic":"method"}],"addSocialMediaHandleWithHttpInfo":[{"__symbolic":"method"}],"addTagForViewOnTransactionWithHttpInfo":[{"__symbolic":"method"}],"addTransactionNarrativeWithHttpInfo":[{"__symbolic":"method"}],"addWhereTagForViewOnTransactionWithHttpInfo":[{"__symbolic":"method"}],"allAccountsAtOneBankWithHttpInfo":[{"__symbolic":"method"}],"bankByIdWithHttpInfo":[{"__symbolic":"method"}],"configWithHttpInfo":[{"__symbolic":"method"}],"corePrivateAccountsAllBanksWithHttpInfo":[{"__symbolic":"method"}],"createAccountWithHttpInfo":[{"__symbolic":"method"}],"createAtmWithHttpInfo":[{"__symbolic":"method"}],"createBankWithHttpInfo":[{"__symbolic":"method"}],"createBranchWithHttpInfo":[{"__symbolic":"method"}],"createCounterpartyWithHttpInfo":[{"__symbolic":"method"}],"createCustomerWithHttpInfo":[{"__symbolic":"method"}],"createMeetingWithHttpInfo":[{"__symbolic":"method"}],"createProductWithHttpInfo":[{"__symbolic":"method"}],"createTransactionTypeWithHttpInfo":[{"__symbolic":"method"}],"createUserWithHttpInfo":[{"__symbolic":"method"}],"createUserCustomerLinksWithHttpInfo":[{"__symbolic":"method"}],"createViewForBankAccountWithHttpInfo":[{"__symbolic":"method"}],"deleteCommentForViewOnTransactionWithHttpInfo":[{"__symbolic":"method"}],"deleteCounterpartyCorporateLocationWithHttpInfo":[{"__symbolic":"method"}],"deleteCounterpartyImageUrlWithHttpInfo":[{"__symbolic":"method"}],"deleteCounterpartyMoreInfoWithHttpInfo":[{"__symbolic":"method"}],"deleteCounterpartyOpenCorporatesUrlWithHttpInfo":[{"__symbolic":"method"}],"deleteCounterpartyPhysicalLocationWithHttpInfo":[{"__symbolic":"method"}],"deleteCounterpartyPrivateAliasWithHttpInfo":[{"__symbolic":"method"}],"deleteCounterpartyPublicAliasWithHttpInfo":[{"__symbolic":"method"}],"deleteCounterpartyUrlWithHttpInfo":[{"__symbolic":"method"}],"deleteEntitlementWithHttpInfo":[{"__symbolic":"method"}],"deleteImageForViewOnTransactionWithHttpInfo":[{"__symbolic":"method"}],"deleteTagForViewOnTransactionWithHttpInfo":[{"__symbolic":"method"}],"deleteTransactionNarrativeWithHttpInfo":[{"__symbolic":"method"}],"deleteViewForBankAccountWithHttpInfo":[{"__symbolic":"method"}],"deleteWhereTagForViewOnTransactionWithHttpInfo":[{"__symbolic":"method"}],"enableDisableConsumersWithHttpInfo":[{"__symbolic":"method"}],"getAdapterWithHttpInfo":[{"__symbolic":"method"}],"getAllEntitlementsWithHttpInfo":[{"__symbolic":"method"}],"getAtmWithHttpInfo":[{"__symbolic":"method"}],"getAtmsWithHttpInfo":[{"__symbolic":"method"}],"getBanksWithHttpInfo":[{"__symbolic":"method"}],"getBranchWithHttpInfo":[{"__symbolic":"method"}],"getBranchesWithHttpInfo":[{"__symbolic":"method"}],"getCardsWithHttpInfo":[{"__symbolic":"method"}],"getCardsForBankWithHttpInfo":[{"__symbolic":"method"}],"getCommentsForViewOnTransactionWithHttpInfo":[{"__symbolic":"method"}],"getConnectorMetricsWithHttpInfo":[{"__symbolic":"method"}],"getConsumerWithHttpInfo":[{"__symbolic":"method"}],"getConsumersWithHttpInfo":[{"__symbolic":"method"}],"getCoreAccountByIdWithHttpInfo":[{"__symbolic":"method"}],"getCoreTransactionsForBankAccountWithHttpInfo":[{"__symbolic":"method"}],"getCounterpartiesForAccountWithHttpInfo":[{"__symbolic":"method"}],"getCounterpartyPublicAliasWithHttpInfo":[{"__symbolic":"method"}],"getCrmEventsWithHttpInfo":[{"__symbolic":"method"}],"getCurrentFxRateWithHttpInfo":[{"__symbolic":"method"}],"getCurrentUserWithHttpInfo":[{"__symbolic":"method"}],"getCustomerWithHttpInfo":[{"__symbolic":"method"}],"getCustomerMessagesWithHttpInfo":[{"__symbolic":"method"}],"getCustomersWithHttpInfo":[{"__symbolic":"method"}],"getEntitlementsWithHttpInfo":[{"__symbolic":"method"}],"getEntitlementsByBankAndUserWithHttpInfo":[{"__symbolic":"method"}],"getImagesForViewOnTransactionWithHttpInfo":[{"__symbolic":"method"}],"getKycChecksWithHttpInfo":[{"__symbolic":"method"}],"getKycDocumentsWithHttpInfo":[{"__symbolic":"method"}],"getKycMediaWithHttpInfo":[{"__symbolic":"method"}],"getKycStatusesWithHttpInfo":[{"__symbolic":"method"}],"getMeetingWithHttpInfo":[{"__symbolic":"method"}],"getMeetingsWithHttpInfo":[{"__symbolic":"method"}],"getMessageDocsWithHttpInfo":[{"__symbolic":"method"}],"getMetricsWithHttpInfo":[{"__symbolic":"method"}],"getOtherAccountByIdForBankAccountWithHttpInfo":[{"__symbolic":"method"}],"getOtherAccountForTransactionWithHttpInfo":[{"__symbolic":"method"}],"getOtherAccountMetadataWithHttpInfo":[{"__symbolic":"method"}],"getOtherAccountPrivateAliasWithHttpInfo":[{"__symbolic":"method"}],"getOtherAccountsForBankAccountWithHttpInfo":[{"__symbolic":"method"}],"getPermissionForUserForBankAccountWithHttpInfo":[{"__symbolic":"method"}],"getPermissionsForBankAccountWithHttpInfo":[{"__symbolic":"method"}],"getProductWithHttpInfo":[{"__symbolic":"method"}],"getProductsWithHttpInfo":[{"__symbolic":"method"}],"getRolesWithHttpInfo":[{"__symbolic":"method"}],"getSocialMediaHandlesWithHttpInfo":[{"__symbolic":"method"}],"getTagsForViewOnTransactionWithHttpInfo":[{"__symbolic":"method"}],"getTransactionByIdForBankAccountWithHttpInfo":[{"__symbolic":"method"}],"getTransactionNarrativeWithHttpInfo":[{"__symbolic":"method"}],"getTransactionRequestTypesWithHttpInfo":[{"__symbolic":"method"}],"getTransactionRequestTypesSupportedByBankWithHttpInfo":[{"__symbolic":"method"}],"getTransactionRequestsWithHttpInfo":[{"__symbolic":"method"}],"getTransactionTypesWithHttpInfo":[{"__symbolic":"method"}],"getTransactionsForBankAccountWithHttpInfo":[{"__symbolic":"method"}],"getUserWithHttpInfo":[{"__symbolic":"method"}],"getUserByUserIdWithHttpInfo":[{"__symbolic":"method"}],"getUserByUsernameWithHttpInfo":[{"__symbolic":"method"}],"getUsersWithHttpInfo":[{"__symbolic":"method"}],"getViewsForBankAccountWithHttpInfo":[{"__symbolic":"method"}],"getWhereTagForViewOnTransactionWithHttpInfo":[{"__symbolic":"method"}],"privateAccountsAtOneBankWithHttpInfo":[{"__symbolic":"method"}],"publicAccountsAllBanksWithHttpInfo":[{"__symbolic":"method"}],"publicAccountsAtOneBankWithHttpInfo":[{"__symbolic":"method"}],"removePermissionForUserForBankAccountForAllViewsWithHttpInfo":[{"__symbolic":"method"}],"removePermissionForUserForBankAccountForOneViewWithHttpInfo":[{"__symbolic":"method"}],"rootWithHttpInfo":[{"__symbolic":"method"}],"sandboxDataImportWithHttpInfo":[{"__symbolic":"method"}],"updateAccountLabelWithHttpInfo":[{"__symbolic":"method"}],"updateBranchWithHttpInfo":[{"__symbolic":"method"}],"updateConsumerRedirectUrlWithHttpInfo":[{"__symbolic":"method"}],"updateCounterpartyCorporateLocationWithHttpInfo":[{"__symbolic":"method"}],"updateCounterpartyImageUrlWithHttpInfo":[{"__symbolic":"method"}],"updateCounterpartyMoreInfoWithHttpInfo":[{"__symbolic":"method"}],"updateCounterpartyOpenCorporatesUrlWithHttpInfo":[{"__symbolic":"method"}],"updateCounterpartyPhysicalLocationWithHttpInfo":[{"__symbolic":"method"}],"updateCounterpartyPrivateAliasWithHttpInfo":[{"__symbolic":"method"}],"updateCounterpartyPublicAliasWithHttpInfo":[{"__symbolic":"method"}],"updateCounterpartyUrlWithHttpInfo":[{"__symbolic":"method"}],"updateTransactionNarrativeWithHttpInfo":[{"__symbolic":"method"}],"updateViewForBankAccountWithHttpInfo":[{"__symbolic":"method"}],"updateWhereTagForViewOnTransactionWithHttpInfo":[{"__symbolic":"method"}]}}}},{"__symbolic":"module","version":1,"metadata":{"DefaultService":{"__symbolic":"class","decorators":[{"__symbolic":"call","expression":{"__symbolic":"reference","module":"@angular/core","name":"Injectable"}}],"members":{"__ctor__":[{"__symbolic":"constructor","parameterDecorators":[null,[{"__symbolic":"call","expression":{"__symbolic":"reference","module":"@angular/core","name":"Optional"}},{"__symbolic":"call","expression":{"__symbolic":"reference","module":"@angular/core","name":"Inject"},"arguments":[{"__symbolic":"reference","module":"../variables","name":"BASE_PATH"}]}],[{"__symbolic":"call","expression":{"__symbolic":"reference","module":"@angular/core","name":"Optional"}}]],"parameters":[{"__symbolic":"reference","module":"@angular/http","name":"Http"},{"__symbolic":"reference","name":"string"},{"__symbolic":"reference","module":"../configuration","name":"Configuration"}]}],"extendObj":[{"__symbolic":"method"}],"canConsumeForm":[{"__symbolic":"method"}],"accountById":[{"__symbolic":"method"}],"addCardsForBank":[{"__symbolic":"method"}],"addCommentForViewOnTransaction":[{"__symbolic":"method"}],"addCounterpartyCorporateLocation":[{"__symbolic":"method"}],"addCounterpartyImageUrl":[{"__symbolic":"method"}],"addCounterpartyMoreInfo":[{"__symbolic":"method"}],"addCounterpartyOpenCorporatesUrl":[{"__symbolic":"method"}],"addCounterpartyPhysicalLocation":[{"__symbolic":"method"}],"addCounterpartyPublicAlias":[{"__symbolic":"method"}],"addCounterpartyUrl":[{"__symbolic":"method"}],"addCustomerMessage":[{"__symbolic":"method"}],"addEntitlement":[{"__symbolic":"method"}],"addImageForViewOnTransaction":[{"__symbolic":"method"}],"addKycCheck":[{"__symbolic":"method"}],"addKycDocument":[{"__symbolic":"method"}],"addKycMedia":[{"__symbolic":"method"}],"addKycStatus":[{"__symbolic":"method"}],"addOtherAccountPrivateAlias":[{"__symbolic":"method"}],"addPermissionForUserForBankAccountForMultipleViews":[{"__symbolic":"method"}],"addPermissionForUserForBankAccountForOneView":[{"__symbolic":"method"}],"addSocialMediaHandle":[{"__symbolic":"method"}],"addTagForViewOnTransaction":[{"__symbolic":"method"}],"addTransactionNarrative":[{"__symbolic":"method"}],"addWhereTagForViewOnTransaction":[{"__symbolic":"method"}],"allAccountsAtOneBank":[{"__symbolic":"method"}],"bankById":[{"__symbolic":"method"}],"config":[{"__symbolic":"method"}],"corePrivateAccountsAllBanks":[{"__symbolic":"method"}],"createAccount":[{"__symbolic":"method"}],"createAtm":[{"__symbolic":"method"}],"createBank":[{"__symbolic":"method"}],"createBranch":[{"__symbolic":"method"}],"createCounterparty":[{"__symbolic":"method"}],"createCustomer":[{"__symbolic":"method"}],"createMeeting":[{"__symbolic":"method"}],"createProduct":[{"__symbolic":"method"}],"createTransactionType":[{"__symbolic":"method"}],"createUser":[{"__symbolic":"method"}],"createUserCustomerLinks":[{"__symbolic":"method"}],"createViewForBankAccount":[{"__symbolic":"method"}],"deleteCommentForViewOnTransaction":[{"__symbolic":"method"}],"deleteCounterpartyCorporateLocation":[{"__symbolic":"method"}],"deleteCounterpartyImageUrl":[{"__symbolic":"method"}],"deleteCounterpartyMoreInfo":[{"__symbolic":"method"}],"deleteCounterpartyOpenCorporatesUrl":[{"__symbolic":"method"}],"deleteCounterpartyPhysicalLocation":[{"__symbolic":"method"}],"deleteCounterpartyPrivateAlias":[{"__symbolic":"method"}],"deleteCounterpartyPublicAlias":[{"__symbolic":"method"}],"deleteCounterpartyUrl":[{"__symbolic":"method"}],"deleteEntitlement":[{"__symbolic":"method"}],"deleteImageForViewOnTransaction":[{"__symbolic":"method"}],"deleteTagForViewOnTransaction":[{"__symbolic":"method"}],"deleteTransactionNarrative":[{"__symbolic":"method"}],"deleteViewForBankAccount":[{"__symbolic":"method"}],"deleteWhereTagForViewOnTransaction":[{"__symbolic":"method"}],"enableDisableConsumers":[{"__symbolic":"method"}],"getAdapter":[{"__symbolic":"method"}],"getAllEntitlements":[{"__symbolic":"method"}],"getAtm":[{"__symbolic":"method"}],"getAtms":[{"__symbolic":"method"}],"getBanks":[{"__symbolic":"method"}],"getBranch":[{"__symbolic":"method"}],"getBranches":[{"__symbolic":"method"}],"getCards":[{"__symbolic":"method"}],"getCardsForBank":[{"__symbolic":"method"}],"getCommentsForViewOnTransaction":[{"__symbolic":"method"}],"getConnectorMetrics":[{"__symbolic":"method"}],"getConsumer":[{"__symbolic":"method"}],"getConsumers":[{"__symbolic":"method"}],"getCoreAccountById":[{"__symbolic":"method"}],"getCoreTransactionsForBankAccount":[{"__symbolic":"method"}],"getCounterpartiesForAccount":[{"__symbolic":"method"}],"getCounterpartyPublicAlias":[{"__symbolic":"method"}],"getCrmEvents":[{"__symbolic":"method"}],"getCurrentFxRate":[{"__symbolic":"method"}],"getCurrentUser":[{"__symbolic":"method"}],"getCustomer":[{"__symbolic":"method"}],"getCustomerMessages":[{"__symbolic":"method"}],"getCustomers":[{"__symbolic":"method"}],"getEntitlements":[{"__symbolic":"method"}],"getEntitlementsByBankAndUser":[{"__symbolic":"method"}],"getImagesForViewOnTransaction":[{"__symbolic":"method"}],"getKycChecks":[{"__symbolic":"method"}],"getKycDocuments":[{"__symbolic":"method"}],"getKycMedia":[{"__symbolic":"method"}],"getKycStatuses":[{"__symbolic":"method"}],"getMeeting":[{"__symbolic":"method"}],"getMeetings":[{"__symbolic":"method"}],"getMessageDocs":[{"__symbolic":"method"}],"getMetrics":[{"__symbolic":"method"}],"getOtherAccountByIdForBankAccount":[{"__symbolic":"method"}],"getOtherAccountForTransaction":[{"__symbolic":"method"}],"getOtherAccountMetadata":[{"__symbolic":"method"}],"getOtherAccountPrivateAlias":[{"__symbolic":"method"}],"getOtherAccountsForBankAccount":[{"__symbolic":"method"}],"getPermissionForUserForBankAccount":[{"__symbolic":"method"}],"getPermissionsForBankAccount":[{"__symbolic":"method"}],"getProduct":[{"__symbolic":"method"}],"getProducts":[{"__symbolic":"method"}],"getRoles":[{"__symbolic":"method"}],"getSocialMediaHandles":[{"__symbolic":"method"}],"getTagsForViewOnTransaction":[{"__symbolic":"method"}],"getTransactionByIdForBankAccount":[{"__symbolic":"method"}],"getTransactionNarrative":[{"__symbolic":"method"}],"getTransactionRequestTypes":[{"__symbolic":"method"}],"getTransactionRequestTypesSupportedByBank":[{"__symbolic":"method"}],"getTransactionRequests":[{"__symbolic":"method"}],"getTransactionTypes":[{"__symbolic":"method"}],"getTransactionsForBankAccount":[{"__symbolic":"method"}],"getUser":[{"__symbolic":"method"}],"getUserByUserId":[{"__symbolic":"method"}],"getUserByUsername":[{"__symbolic":"method"}],"getUsers":[{"__symbolic":"method"}],"getViewsForBankAccount":[{"__symbolic":"method"}],"getWhereTagForViewOnTransaction":[{"__symbolic":"method"}],"privateAccountsAtOneBank":[{"__symbolic":"method"}],"publicAccountsAllBanks":[{"__symbolic":"method"}],"publicAccountsAtOneBank":[{"__symbolic":"method"}],"removePermissionForUserForBankAccountForAllViews":[{"__symbolic":"method"}],"removePermissionForUserForBankAccountForOneView":[{"__symbolic":"method"}],"root":[{"__symbolic":"method"}],"sandboxDataImport":[{"__symbolic":"method"}],"updateAccountLabel":[{"__symbolic":"method"}],"updateBranch":[{"__symbolic":"method"}],"updateConsumerRedirectUrl":[{"__symbolic":"method"}],"updateCounterpartyCorporateLocation":[{"__symbolic":"method"}],"updateCounterpartyImageUrl":[{"__symbolic":"method"}],"updateCounterpartyMoreInfo":[{"__symbolic":"method"}],"updateCounterpartyOpenCorporatesUrl":[{"__symbolic":"method"}],"updateCounterpartyPhysicalLocation":[{"__symbolic":"method"}],"updateCounterpartyPrivateAlias":[{"__symbolic":"method"}],"updateCounterpartyPublicAlias":[{"__symbolic":"method"}],"updateCounterpartyUrl":[{"__symbolic":"method"}],"updateTransactionNarrative":[{"__symbolic":"method"}],"updateViewForBankAccount":[{"__symbolic":"method"}],"updateWhereTagForViewOnTransaction":[{"__symbolic":"method"}],"accountByIdWithHttpInfo":[{"__symbolic":"method"}],"addCardsForBankWithHttpInfo":[{"__symbolic":"method"}],"addCommentForViewOnTransactionWithHttpInfo":[{"__symbolic":"method"}],"addCounterpartyCorporateLocationWithHttpInfo":[{"__symbolic":"method"}],"addCounterpartyImageUrlWithHttpInfo":[{"__symbolic":"method"}],"addCounterpartyMoreInfoWithHttpInfo":[{"__symbolic":"method"}],"addCounterpartyOpenCorporatesUrlWithHttpInfo":[{"__symbolic":"method"}],"addCounterpartyPhysicalLocationWithHttpInfo":[{"__symbolic":"method"}],"addCounterpartyPublicAliasWithHttpInfo":[{"__symbolic":"method"}],"addCounterpartyUrlWithHttpInfo":[{"__symbolic":"method"}],"addCustomerMessageWithHttpInfo":[{"__symbolic":"method"}],"addEntitlementWithHttpInfo":[{"__symbolic":"method"}],"addImageForViewOnTransactionWithHttpInfo":[{"__symbolic":"method"}],"addKycCheckWithHttpInfo":[{"__symbolic":"method"}],"addKycDocumentWithHttpInfo":[{"__symbolic":"method"}],"addKycMediaWithHttpInfo":[{"__symbolic":"method"}],"addKycStatusWithHttpInfo":[{"__symbolic":"method"}],"addOtherAccountPrivateAliasWithHttpInfo":[{"__symbolic":"method"}],"addPermissionForUserForBankAccountForMultipleViewsWithHttpInfo":[{"__symbolic":"method"}],"addPermissionForUserForBankAccountForOneViewWithHttpInfo":[{"__symbolic":"method"}],"addSocialMediaHandleWithHttpInfo":[{"__symbolic":"method"}],"addTagForViewOnTransactionWithHttpInfo":[{"__symbolic":"method"}],"addTransactionNarrativeWithHttpInfo":[{"__symbolic":"method"}],"addWhereTagForViewOnTransactionWithHttpInfo":[{"__symbolic":"method"}],"allAccountsAtOneBankWithHttpInfo":[{"__symbolic":"method"}],"bankByIdWithHttpInfo":[{"__symbolic":"method"}],"configWithHttpInfo":[{"__symbolic":"method"}],"corePrivateAccountsAllBanksWithHttpInfo":[{"__symbolic":"method"}],"createAccountWithHttpInfo":[{"__symbolic":"method"}],"createAtmWithHttpInfo":[{"__symbolic":"method"}],"createBankWithHttpInfo":[{"__symbolic":"method"}],"createBranchWithHttpInfo":[{"__symbolic":"method"}],"createCounterpartyWithHttpInfo":[{"__symbolic":"method"}],"createCustomerWithHttpInfo":[{"__symbolic":"method"}],"createMeetingWithHttpInfo":[{"__symbolic":"method"}],"createProductWithHttpInfo":[{"__symbolic":"method"}],"createTransactionTypeWithHttpInfo":[{"__symbolic":"method"}],"createUserWithHttpInfo":[{"__symbolic":"method"}],"createUserCustomerLinksWithHttpInfo":[{"__symbolic":"method"}],"createViewForBankAccountWithHttpInfo":[{"__symbolic":"method"}],"deleteCommentForViewOnTransactionWithHttpInfo":[{"__symbolic":"method"}],"deleteCounterpartyCorporateLocationWithHttpInfo":[{"__symbolic":"method"}],"deleteCounterpartyImageUrlWithHttpInfo":[{"__symbolic":"method"}],"deleteCounterpartyMoreInfoWithHttpInfo":[{"__symbolic":"method"}],"deleteCounterpartyOpenCorporatesUrlWithHttpInfo":[{"__symbolic":"method"}],"deleteCounterpartyPhysicalLocationWithHttpInfo":[{"__symbolic":"method"}],"deleteCounterpartyPrivateAliasWithHttpInfo":[{"__symbolic":"method"}],"deleteCounterpartyPublicAliasWithHttpInfo":[{"__symbolic":"method"}],"deleteCounterpartyUrlWithHttpInfo":[{"__symbolic":"method"}],"deleteEntitlementWithHttpInfo":[{"__symbolic":"method"}],"deleteImageForViewOnTransactionWithHttpInfo":[{"__symbolic":"method"}],"deleteTagForViewOnTransactionWithHttpInfo":[{"__symbolic":"method"}],"deleteTransactionNarrativeWithHttpInfo":[{"__symbolic":"method"}],"deleteViewForBankAccountWithHttpInfo":[{"__symbolic":"method"}],"deleteWhereTagForViewOnTransactionWithHttpInfo":[{"__symbolic":"method"}],"enableDisableConsumersWithHttpInfo":[{"__symbolic":"method"}],"getAdapterWithHttpInfo":[{"__symbolic":"method"}],"getAllEntitlementsWithHttpInfo":[{"__symbolic":"method"}],"getAtmWithHttpInfo":[{"__symbolic":"method"}],"getAtmsWithHttpInfo":[{"__symbolic":"method"}],"getBanksWithHttpInfo":[{"__symbolic":"method"}],"getBranchWithHttpInfo":[{"__symbolic":"method"}],"getBranchesWithHttpInfo":[{"__symbolic":"method"}],"getCardsWithHttpInfo":[{"__symbolic":"method"}],"getCardsForBankWithHttpInfo":[{"__symbolic":"method"}],"getCommentsForViewOnTransactionWithHttpInfo":[{"__symbolic":"method"}],"getConnectorMetricsWithHttpInfo":[{"__symbolic":"method"}],"getConsumerWithHttpInfo":[{"__symbolic":"method"}],"getConsumersWithHttpInfo":[{"__symbolic":"method"}],"getCoreAccountByIdWithHttpInfo":[{"__symbolic":"method"}],"getCoreTransactionsForBankAccountWithHttpInfo":[{"__symbolic":"method"}],"getCounterpartiesForAccountWithHttpInfo":[{"__symbolic":"method"}],"getCounterpartyPublicAliasWithHttpInfo":[{"__symbolic":"method"}],"getCrmEventsWithHttpInfo":[{"__symbolic":"method"}],"getCurrentFxRateWithHttpInfo":[{"__symbolic":"method"}],"getCurrentUserWithHttpInfo":[{"__symbolic":"method"}],"getCustomerWithHttpInfo":[{"__symbolic":"method"}],"getCustomerMessagesWithHttpInfo":[{"__symbolic":"method"}],"getCustomersWithHttpInfo":[{"__symbolic":"method"}],"getEntitlementsWithHttpInfo":[{"__symbolic":"method"}],"getEntitlementsByBankAndUserWithHttpInfo":[{"__symbolic":"method"}],"getImagesForViewOnTransactionWithHttpInfo":[{"__symbolic":"method"}],"getKycChecksWithHttpInfo":[{"__symbolic":"method"}],"getKycDocumentsWithHttpInfo":[{"__symbolic":"method"}],"getKycMediaWithHttpInfo":[{"__symbolic":"method"}],"getKycStatusesWithHttpInfo":[{"__symbolic":"method"}],"getMeetingWithHttpInfo":[{"__symbolic":"method"}],"getMeetingsWithHttpInfo":[{"__symbolic":"method"}],"getMessageDocsWithHttpInfo":[{"__symbolic":"method"}],"getMetricsWithHttpInfo":[{"__symbolic":"method"}],"getOtherAccountByIdForBankAccountWithHttpInfo":[{"__symbolic":"method"}],"getOtherAccountForTransactionWithHttpInfo":[{"__symbolic":"method"}],"getOtherAccountMetadataWithHttpInfo":[{"__symbolic":"method"}],"getOtherAccountPrivateAliasWithHttpInfo":[{"__symbolic":"method"}],"getOtherAccountsForBankAccountWithHttpInfo":[{"__symbolic":"method"}],"getPermissionForUserForBankAccountWithHttpInfo":[{"__symbolic":"method"}],"getPermissionsForBankAccountWithHttpInfo":[{"__symbolic":"method"}],"getProductWithHttpInfo":[{"__symbolic":"method"}],"getProductsWithHttpInfo":[{"__symbolic":"method"}],"getRolesWithHttpInfo":[{"__symbolic":"method"}],"getSocialMediaHandlesWithHttpInfo":[{"__symbolic":"method"}],"getTagsForViewOnTransactionWithHttpInfo":[{"__symbolic":"method"}],"getTransactionByIdForBankAccountWithHttpInfo":[{"__symbolic":"method"}],"getTransactionNarrativeWithHttpInfo":[{"__symbolic":"method"}],"getTransactionRequestTypesWithHttpInfo":[{"__symbolic":"method"}],"getTransactionRequestTypesSupportedByBankWithHttpInfo":[{"__symbolic":"method"}],"getTransactionRequestsWithHttpInfo":[{"__symbolic":"method"}],"getTransactionTypesWithHttpInfo":[{"__symbolic":"method"}],"getTransactionsForBankAccountWithHttpInfo":[{"__symbolic":"method"}],"getUserWithHttpInfo":[{"__symbolic":"method"}],"getUserByUserIdWithHttpInfo":[{"__symbolic":"method"}],"getUserByUsernameWithHttpInfo":[{"__symbolic":"method"}],"getUsersWithHttpInfo":[{"__symbolic":"method"}],"getViewsForBankAccountWithHttpInfo":[{"__symbolic":"method"}],"getWhereTagForViewOnTransactionWithHttpInfo":[{"__symbolic":"method"}],"privateAccountsAtOneBankWithHttpInfo":[{"__symbolic":"method"}],"publicAccountsAllBanksWithHttpInfo":[{"__symbolic":"method"}],"publicAccountsAtOneBankWithHttpInfo":[{"__symbolic":"method"}],"removePermissionForUserForBankAccountForAllViewsWithHttpInfo":[{"__symbolic":"method"}],"removePermissionForUserForBankAccountForOneViewWithHttpInfo":[{"__symbolic":"method"}],"rootWithHttpInfo":[{"__symbolic":"method"}],"sandboxDataImportWithHttpInfo":[{"__symbolic":"method"}],"updateAccountLabelWithHttpInfo":[{"__symbolic":"method"}],"updateBranchWithHttpInfo":[{"__symbolic":"method"}],"updateConsumerRedirectUrlWithHttpInfo":[{"__symbolic":"method"}],"updateCounterpartyCorporateLocationWithHttpInfo":[{"__symbolic":"method"}],"updateCounterpartyImageUrlWithHttpInfo":[{"__symbolic":"method"}],"updateCounterpartyMoreInfoWithHttpInfo":[{"__symbolic":"method"}],"updateCounterpartyOpenCorporatesUrlWithHttpInfo":[{"__symbolic":"method"}],"updateCounterpartyPhysicalLocationWithHttpInfo":[{"__symbolic":"method"}],"updateCounterpartyPrivateAliasWithHttpInfo":[{"__symbolic":"method"}],"updateCounterpartyPublicAliasWithHttpInfo":[{"__symbolic":"method"}],"updateCounterpartyUrlWithHttpInfo":[{"__symbolic":"method"}],"updateTransactionNarrativeWithHttpInfo":[{"__symbolic":"method"}],"updateViewForBankAccountWithHttpInfo":[{"__symbolic":"method"}],"updateWhereTagForViewOnTransactionWithHttpInfo":[{"__symbolic":"method"}]}}}}]